{
    "py/object": "models.course.Course",
    "id": 154940,
    "name": "\u7269\u7406\u521b\u65b0\u80fd\u529b\u5bfc\u5f15",
    "courseCode": "PHYS4702",
    "lessonCode": "PHYS4702.28",
    "teacherName": "\u6731\u6587\u5149",
    "lectures": [
        {
            "py/object": "models.lecture.Lecture",
            "startDate": 1709551800,
            "endDate": 1709557500,
            "name": "\u7269\u7406\u521b\u65b0\u80fd\u529b\u5bfc\u5f15",
            "location": "2303",
            "teacherName": "\u6731\u6587\u5149",
            "periods": 2,
            "additionalInfo": {},
            "startIndex": 11,
            "endIndex": 12
        }
    ],
    "description": "2\u5468 2303 :1(11,12) \u6731\u6587\u5149",
    "credit": 3,
    "additionalInfo": {}
}