{
    "py/object": "models.course.Course",
    "id": 94659,
    "name": "\u4ea4\u6362\u4ee3\u6570",
    "courseCode": "MA04410",
    "lessonCode": "MA04410.01",
    "teacherName": "\u9c81\u5b66\u661f",
    "lectures": [
        {
            "py/object": "models.lecture.Lecture",
            "startDate": 1473926100,
            "endDate": 1473931800,
            "name": "\u4ea4\u6362\u4ee3\u6570",
            "location": "5307",
            "teacherName": "\u9c81\u5b66\u661f",
            "periods": 2,
            "additionalInfo": {}
        },
        {
            "py/object": "models.lecture.Lecture",
            "startDate": 1474098900,
            "endDate": 1474104600,
            "name": "\u4ea4\u6362\u4ee3\u6570",
            "location": "5307",
            "teacherName": "\u9c81\u5b66\u661f",
            "periods": 2,
            "additionalInfo": {}
        },
        {
            "py/object": "models.lecture.Lecture",
            "startDate": 1474530900,
            "endDate": 1474536600,
            "name": "\u4ea4\u6362\u4ee3\u6570",
            "location": "5307",
            "teacherName": "\u9c81\u5b66\u661f",
            "periods": 2,
            "additionalInfo": {}
        },
        {
            "py/object": "models.lecture.Lecture",
            "startDate": 1474703700,
            "endDate": 1474709400,
            "name": "\u4ea4\u6362\u4ee3\u6570",
            "location": "5307",
            "teacherName": "\u9c81\u5b66\u661f",
            "periods": 2,
            "additionalInfo": {}
        },
        {
            "py/object": "models.lecture.Lecture",
            "startDate": 1475135700,
            "endDate": 1475141400,
            "name": "\u4ea4\u6362\u4ee3\u6570",
            "location": "5307",
            "teacherName": "\u9c81\u5b66\u661f",
            "periods": 2,
            "additionalInfo": {}
        },
        {
            "py/object": "models.lecture.Lecture",
            "startDate": 1475308500,
            "endDate": 1475314200,
            "name": "\u4ea4\u6362\u4ee3\u6570",
            "location": "5307",
            "teacherName": "\u9c81\u5b66\u661f",
            "periods": 2,
            "additionalInfo": {}
        },
        {
            "py/object": "models.lecture.Lecture",
            "startDate": 1475740500,
            "endDate": 1475746200,
            "name": "\u4ea4\u6362\u4ee3\u6570",
            "location": "5307",
            "teacherName": "\u9c81\u5b66\u661f",
            "periods": 2,
            "additionalInfo": {}
        },
        {
            "py/object": "models.lecture.Lecture",
            "startDate": 1475913300,
            "endDate": 1475919000,
            "name": "\u4ea4\u6362\u4ee3\u6570",
            "location": "5307",
            "teacherName": "\u9c81\u5b66\u661f",
            "periods": 2,
            "additionalInfo": {}
        },
        {
            "py/object": "models.lecture.Lecture",
            "startDate": 1476345300,
            "endDate": 1476351000,
            "name": "\u4ea4\u6362\u4ee3\u6570",
            "location": "5307",
            "teacherName": "\u9c81\u5b66\u661f",
            "periods": 2,
            "additionalInfo": {}
        },
        {
            "py/object": "models.lecture.Lecture",
            "startDate": 1476518100,
            "endDate": 1476523800,
            "name": "\u4ea4\u6362\u4ee3\u6570",
            "location": "5307",
            "teacherName": "\u9c81\u5b66\u661f",
            "periods": 2,
            "additionalInfo": {}
        },
        {
            "py/object": "models.lecture.Lecture",
            "startDate": 1476950100,
            "endDate": 1476955800,
            "name": "\u4ea4\u6362\u4ee3\u6570",
            "location": "5307",
            "teacherName": "\u9c81\u5b66\u661f",
            "periods": 2,
            "additionalInfo": {}
        },
        {
            "py/object": "models.lecture.Lecture",
            "startDate": 1477122900,
            "endDate": 1477128600,
            "name": "\u4ea4\u6362\u4ee3\u6570",
            "location": "5307",
            "teacherName": "\u9c81\u5b66\u661f",
            "periods": 2,
            "additionalInfo": {}
        },
        {
            "py/object": "models.lecture.Lecture",
            "startDate": 1477554900,
            "endDate": 1477560600,
            "name": "\u4ea4\u6362\u4ee3\u6570",
            "location": "5307",
            "teacherName": "\u9c81\u5b66\u661f",
            "periods": 2,
            "additionalInfo": {}
        },
        {
            "py/object": "models.lecture.Lecture",
            "startDate": 1477727700,
            "endDate": 1477733400,
            "name": "\u4ea4\u6362\u4ee3\u6570",
            "location": "5307",
            "teacherName": "\u9c81\u5b66\u661f",
            "periods": 2,
            "additionalInfo": {}
        },
        {
            "py/object": "models.lecture.Lecture",
            "startDate": 1478159700,
            "endDate": 1478165400,
            "name": "\u4ea4\u6362\u4ee3\u6570",
            "location": "5307",
            "teacherName": "\u9c81\u5b66\u661f",
            "periods": 2,
            "additionalInfo": {}
        },
        {
            "py/object": "models.lecture.Lecture",
            "startDate": 1478332500,
            "endDate": 1478338200,
            "name": "\u4ea4\u6362\u4ee3\u6570",
            "location": "5307",
            "teacherName": "\u9c81\u5b66\u661f",
            "periods": 2,
            "additionalInfo": {}
        },
        {
            "py/object": "models.lecture.Lecture",
            "startDate": 1478764500,
            "endDate": 1478770200,
            "name": "\u4ea4\u6362\u4ee3\u6570",
            "location": "5307",
            "teacherName": "\u9c81\u5b66\u661f",
            "periods": 2,
            "additionalInfo": {}
        },
        {
            "py/object": "models.lecture.Lecture",
            "startDate": 1478937300,
            "endDate": 1478943000,
            "name": "\u4ea4\u6362\u4ee3\u6570",
            "location": "5307",
            "teacherName": "\u9c81\u5b66\u661f",
            "periods": 2,
            "additionalInfo": {}
        },
        {
            "py/object": "models.lecture.Lecture",
            "startDate": 1479369300,
            "endDate": 1479375000,
            "name": "\u4ea4\u6362\u4ee3\u6570",
            "location": "5307",
            "teacherName": "\u9c81\u5b66\u661f",
            "periods": 2,
            "additionalInfo": {}
        },
        {
            "py/object": "models.lecture.Lecture",
            "startDate": 1479542100,
            "endDate": 1479547800,
            "name": "\u4ea4\u6362\u4ee3\u6570",
            "location": "5307",
            "teacherName": "\u9c81\u5b66\u661f",
            "periods": 2,
            "additionalInfo": {}
        },
        {
            "py/object": "models.lecture.Lecture",
            "startDate": 1479974100,
            "endDate": 1479979800,
            "name": "\u4ea4\u6362\u4ee3\u6570",
            "location": "5307",
            "teacherName": "\u9c81\u5b66\u661f",
            "periods": 2,
            "additionalInfo": {}
        },
        {
            "py/object": "models.lecture.Lecture",
            "startDate": 1480146900,
            "endDate": 1480152600,
            "name": "\u4ea4\u6362\u4ee3\u6570",
            "location": "5307",
            "teacherName": "\u9c81\u5b66\u661f",
            "periods": 2,
            "additionalInfo": {}
        },
        {
            "py/object": "models.lecture.Lecture",
            "startDate": 1480578900,
            "endDate": 1480584600,
            "name": "\u4ea4\u6362\u4ee3\u6570",
            "location": "5307",
            "teacherName": "\u9c81\u5b66\u661f",
            "periods": 2,
            "additionalInfo": {}
        },
        {
            "py/object": "models.lecture.Lecture",
            "startDate": 1480751700,
            "endDate": 1480757400,
            "name": "\u4ea4\u6362\u4ee3\u6570",
            "location": "5307",
            "teacherName": "\u9c81\u5b66\u661f",
            "periods": 2,
            "additionalInfo": {}
        },
        {
            "py/object": "models.lecture.Lecture",
            "startDate": 1481183700,
            "endDate": 1481189400,
            "name": "\u4ea4\u6362\u4ee3\u6570",
            "location": "5307",
            "teacherName": "\u9c81\u5b66\u661f",
            "periods": 2,
            "additionalInfo": {}
        },
        {
            "py/object": "models.lecture.Lecture",
            "startDate": 1481356500,
            "endDate": 1481362200,
            "name": "\u4ea4\u6362\u4ee3\u6570",
            "location": "5307",
            "teacherName": "\u9c81\u5b66\u661f",
            "periods": 2,
            "additionalInfo": {}
        },
        {
            "py/object": "models.lecture.Lecture",
            "startDate": 1481788500,
            "endDate": 1481794200,
            "name": "\u4ea4\u6362\u4ee3\u6570",
            "location": "5307",
            "teacherName": "\u9c81\u5b66\u661f",
            "periods": 2,
            "additionalInfo": {}
        },
        {
            "py/object": "models.lecture.Lecture",
            "startDate": 1481961300,
            "endDate": 1481967000,
            "name": "\u4ea4\u6362\u4ee3\u6570",
            "location": "5307",
            "teacherName": "\u9c81\u5b66\u661f",
            "periods": 2,
            "additionalInfo": {}
        },
        {
            "py/object": "models.lecture.Lecture",
            "startDate": 1482393300,
            "endDate": 1482399000,
            "name": "\u4ea4\u6362\u4ee3\u6570",
            "location": "5307",
            "teacherName": "\u9c81\u5b66\u661f",
            "periods": 2,
            "additionalInfo": {}
        },
        {
            "py/object": "models.lecture.Lecture",
            "startDate": 1482566100,
            "endDate": 1482571800,
            "name": "\u4ea4\u6362\u4ee3\u6570",
            "location": "5307",
            "teacherName": "\u9c81\u5b66\u661f",
            "periods": 2,
            "additionalInfo": {}
        },
        {
            "py/object": "models.lecture.Lecture",
            "startDate": 1482998100,
            "endDate": 1483003800,
            "name": "\u4ea4\u6362\u4ee3\u6570",
            "location": "5307",
            "teacherName": "\u9c81\u5b66\u661f",
            "periods": 2,
            "additionalInfo": {}
        },
        {
            "py/object": "models.lecture.Lecture",
            "startDate": 1483170900,
            "endDate": 1483176600,
            "name": "\u4ea4\u6362\u4ee3\u6570",
            "location": "5307",
            "teacherName": "\u9c81\u5b66\u661f",
            "periods": 2,
            "additionalInfo": {}
        }
    ],
    "description": "3~18\u5468 5307 :4(8,9) \u9c81\u5b66\u661f\n3~18\u5468 5307 :6(8,9) \u9c81\u5b66\u661f",
    "credit": 4,
    "additionalInfo": {}
}