{
    "py/object": "models.course.Course",
    "id": 132306,
    "name": "\u6570\u636e\u5206\u6790\u53ca\u5b9e\u8df5",
    "courseCode": "DS3001",
    "lessonCode": "DS3001.01",
    "teacherName": "\u5218\u6dc7",
    "lectures": [
        {
            "py/object": "models.lecture.Lecture",
            "startDate": 1615190100,
            "endDate": 1615198800,
            "name": "\u6570\u636e\u5206\u6790\u53ca\u5b9e\u8df5",
            "location": "3A107",
            "teacherName": "\u5218\u6dc7",
            "periods": 3,
            "startIndex": 8,
            "endIndex": 10,
            "startHHMM": 1555,
            "endHHMM": 1820,
            "additionalInfo": {}
        },
        {
            "py/object": "models.lecture.Lecture",
            "startDate": 1615794900,
            "endDate": 1615803600,
            "name": "\u6570\u636e\u5206\u6790\u53ca\u5b9e\u8df5",
            "location": "3A107",
            "teacherName": "\u5218\u6dc7",
            "periods": 3,
            "startIndex": 8,
            "endIndex": 10,
            "startHHMM": 1555,
            "endHHMM": 1820,
            "additionalInfo": {}
        },
        {
            "py/object": "models.lecture.Lecture",
            "startDate": 1616399700,
            "endDate": 1616408400,
            "name": "\u6570\u636e\u5206\u6790\u53ca\u5b9e\u8df5",
            "location": "3A107",
            "teacherName": "\u5218\u6dc7",
            "periods": 3,
            "startIndex": 8,
            "endIndex": 10,
            "startHHMM": 1555,
            "endHHMM": 1820,
            "additionalInfo": {}
        },
        {
            "py/object": "models.lecture.Lecture",
            "startDate": 1617004500,
            "endDate": 1617013200,
            "name": "\u6570\u636e\u5206\u6790\u53ca\u5b9e\u8df5",
            "location": "3A107",
            "teacherName": "\u5218\u6dc7",
            "periods": 3,
            "startIndex": 8,
            "endIndex": 10,
            "startHHMM": 1555,
            "endHHMM": 1820,
            "additionalInfo": {}
        },
        {
            "py/object": "models.lecture.Lecture",
            "startDate": 1617609300,
            "endDate": 1617618000,
            "name": "\u6570\u636e\u5206\u6790\u53ca\u5b9e\u8df5",
            "location": "3A107",
            "teacherName": "\u5218\u6dc7",
            "periods": 3,
            "startIndex": 8,
            "endIndex": 10,
            "startHHMM": 1555,
            "endHHMM": 1820,
            "additionalInfo": {}
        },
        {
            "py/object": "models.lecture.Lecture",
            "startDate": 1618214100,
            "endDate": 1618222800,
            "name": "\u6570\u636e\u5206\u6790\u53ca\u5b9e\u8df5",
            "location": "3A107",
            "teacherName": "\u5218\u6dc7",
            "periods": 3,
            "startIndex": 8,
            "endIndex": 10,
            "startHHMM": 1555,
            "endHHMM": 1820,
            "additionalInfo": {}
        },
        {
            "py/object": "models.lecture.Lecture",
            "startDate": 1618818900,
            "endDate": 1618827600,
            "name": "\u6570\u636e\u5206\u6790\u53ca\u5b9e\u8df5",
            "location": "3A107",
            "teacherName": "\u5218\u6dc7",
            "periods": 3,
            "startIndex": 8,
            "endIndex": 10,
            "startHHMM": 1555,
            "endHHMM": 1820,
            "additionalInfo": {}
        },
        {
            "py/object": "models.lecture.Lecture",
            "startDate": 1619423700,
            "endDate": 1619432400,
            "name": "\u6570\u636e\u5206\u6790\u53ca\u5b9e\u8df5",
            "location": "3A107",
            "teacherName": "\u5218\u6dc7",
            "periods": 3,
            "startIndex": 8,
            "endIndex": 10,
            "startHHMM": 1555,
            "endHHMM": 1820,
            "additionalInfo": {}
        },
        {
            "py/object": "models.lecture.Lecture",
            "startDate": 1620028500,
            "endDate": 1620037200,
            "name": "\u6570\u636e\u5206\u6790\u53ca\u5b9e\u8df5",
            "location": "3A107",
            "teacherName": "\u5218\u6dc7",
            "periods": 3,
            "startIndex": 8,
            "endIndex": 10,
            "startHHMM": 1555,
            "endHHMM": 1820,
            "additionalInfo": {}
        },
        {
            "py/object": "models.lecture.Lecture",
            "startDate": 1620633300,
            "endDate": 1620642000,
            "name": "\u6570\u636e\u5206\u6790\u53ca\u5b9e\u8df5",
            "location": "3A107",
            "teacherName": "\u5218\u6dc7",
            "periods": 3,
            "startIndex": 8,
            "endIndex": 10,
            "startHHMM": 1555,
            "endHHMM": 1820,
            "additionalInfo": {}
        },
        {
            "py/object": "models.lecture.Lecture",
            "startDate": 1621238100,
            "endDate": 1621246800,
            "name": "\u6570\u636e\u5206\u6790\u53ca\u5b9e\u8df5",
            "location": "3A107",
            "teacherName": "\u5218\u6dc7",
            "periods": 3,
            "startIndex": 8,
            "endIndex": 10,
            "startHHMM": 1555,
            "endHHMM": 1820,
            "additionalInfo": {}
        },
        {
            "py/object": "models.lecture.Lecture",
            "startDate": 1621842900,
            "endDate": 1621851600,
            "name": "\u6570\u636e\u5206\u6790\u53ca\u5b9e\u8df5",
            "location": "3A107",
            "teacherName": "\u5218\u6dc7",
            "periods": 3,
            "startIndex": 8,
            "endIndex": 10,
            "startHHMM": 1555,
            "endHHMM": 1820,
            "additionalInfo": {}
        },
        {
            "py/object": "models.lecture.Lecture",
            "startDate": 1622447700,
            "endDate": 1622456400,
            "name": "\u6570\u636e\u5206\u6790\u53ca\u5b9e\u8df5",
            "location": "3A107",
            "teacherName": "\u5218\u6dc7",
            "periods": 3,
            "startIndex": 8,
            "endIndex": 10,
            "startHHMM": 1555,
            "endHHMM": 1820,
            "additionalInfo": {}
        },
        {
            "py/object": "models.lecture.Lecture",
            "startDate": 1623052500,
            "endDate": 1623061200,
            "name": "\u6570\u636e\u5206\u6790\u53ca\u5b9e\u8df5",
            "location": "3A107",
            "teacherName": "\u5218\u6dc7",
            "periods": 3,
            "startIndex": 8,
            "endIndex": 10,
            "startHHMM": 1555,
            "endHHMM": 1820,
            "additionalInfo": {}
        }
    ],
    "exams": [],
    "dateTimePlacePersonText": "1~14\u5468 3A107 :1(8,9,10) \u5218\u6dc7",
    "courseType": "\u7406\u8bba\u5b9e\u9a8c\u8bfe",
    "courseGradation": "\u4e13\u4e1a\u6838\u5fc3",
    "courseCategory": "\u672c\u79d1\u8ba1\u5212\u5185\u8bfe\u7a0b",
    "educationType": "\u672c\u79d1",
    "classType": "\u8ba1\u5212\u5185\u4e0e\u81ea\u7531\u9009\u4fee",
    "openDepartment": "\u4eba\u5de5\u667a\u80fd\u4e0e\u6570\u636e\u79d1\u5b66\u5b66\u9662",
    "description": "",
    "credit": 3,
    "additionalInfo": {}
}