{
    "py/object": "models.course.Course",
    "id": 98650,
    "name": "\u91cf\u5b50\u4fe1\u606f\u6280\u672f",
    "courseCode": "002102",
    "lessonCode": "002102.01",
    "teacherName": "\u97e9\u6b63\u752b",
    "lectures": [
        {
            "py/object": "models.lecture.Lecture",
            "startDate": 1094694300,
            "endDate": 1094700000,
            "name": "\u91cf\u5b50\u4fe1\u606f\u6280\u672f",
            "location": null,
            "teacherName": "\u97e9\u6b63\u752b",
            "periods": 2,
            "additionalInfo": {}
        },
        {
            "py/object": "models.lecture.Lecture",
            "startDate": 1095299100,
            "endDate": 1095304800,
            "name": "\u91cf\u5b50\u4fe1\u606f\u6280\u672f",
            "location": null,
            "teacherName": "\u97e9\u6b63\u752b",
            "periods": 2,
            "additionalInfo": {}
        },
        {
            "py/object": "models.lecture.Lecture",
            "startDate": 1095903900,
            "endDate": 1095909600,
            "name": "\u91cf\u5b50\u4fe1\u606f\u6280\u672f",
            "location": null,
            "teacherName": "\u97e9\u6b63\u752b",
            "periods": 2,
            "additionalInfo": {}
        },
        {
            "py/object": "models.lecture.Lecture",
            "startDate": 1096508700,
            "endDate": 1096514400,
            "name": "\u91cf\u5b50\u4fe1\u606f\u6280\u672f",
            "location": null,
            "teacherName": "\u97e9\u6b63\u752b",
            "periods": 2,
            "additionalInfo": {}
        },
        {
            "py/object": "models.lecture.Lecture",
            "startDate": 1097113500,
            "endDate": 1097119200,
            "name": "\u91cf\u5b50\u4fe1\u606f\u6280\u672f",
            "location": null,
            "teacherName": "\u97e9\u6b63\u752b",
            "periods": 2,
            "additionalInfo": {}
        },
        {
            "py/object": "models.lecture.Lecture",
            "startDate": 1097718300,
            "endDate": 1097724000,
            "name": "\u91cf\u5b50\u4fe1\u606f\u6280\u672f",
            "location": null,
            "teacherName": "\u97e9\u6b63\u752b",
            "periods": 2,
            "additionalInfo": {}
        },
        {
            "py/object": "models.lecture.Lecture",
            "startDate": 1098323100,
            "endDate": 1098328800,
            "name": "\u91cf\u5b50\u4fe1\u606f\u6280\u672f",
            "location": null,
            "teacherName": "\u97e9\u6b63\u752b",
            "periods": 2,
            "additionalInfo": {}
        },
        {
            "py/object": "models.lecture.Lecture",
            "startDate": 1098927900,
            "endDate": 1098933600,
            "name": "\u91cf\u5b50\u4fe1\u606f\u6280\u672f",
            "location": null,
            "teacherName": "\u97e9\u6b63\u752b",
            "periods": 2,
            "additionalInfo": {}
        },
        {
            "py/object": "models.lecture.Lecture",
            "startDate": 1099532700,
            "endDate": 1099538400,
            "name": "\u91cf\u5b50\u4fe1\u606f\u6280\u672f",
            "location": null,
            "teacherName": "\u97e9\u6b63\u752b",
            "periods": 2,
            "additionalInfo": {}
        },
        {
            "py/object": "models.lecture.Lecture",
            "startDate": 1100137500,
            "endDate": 1100143200,
            "name": "\u91cf\u5b50\u4fe1\u606f\u6280\u672f",
            "location": null,
            "teacherName": "\u97e9\u6b63\u752b",
            "periods": 2,
            "additionalInfo": {}
        },
        {
            "py/object": "models.lecture.Lecture",
            "startDate": 1100742300,
            "endDate": 1100748000,
            "name": "\u91cf\u5b50\u4fe1\u606f\u6280\u672f",
            "location": null,
            "teacherName": "\u97e9\u6b63\u752b",
            "periods": 2,
            "additionalInfo": {}
        },
        {
            "py/object": "models.lecture.Lecture",
            "startDate": 1101347100,
            "endDate": 1101352800,
            "name": "\u91cf\u5b50\u4fe1\u606f\u6280\u672f",
            "location": null,
            "teacherName": "\u97e9\u6b63\u752b",
            "periods": 2,
            "additionalInfo": {}
        },
        {
            "py/object": "models.lecture.Lecture",
            "startDate": 1101951900,
            "endDate": 1101957600,
            "name": "\u91cf\u5b50\u4fe1\u606f\u6280\u672f",
            "location": null,
            "teacherName": "\u97e9\u6b63\u752b",
            "periods": 2,
            "additionalInfo": {}
        },
        {
            "py/object": "models.lecture.Lecture",
            "startDate": 1102556700,
            "endDate": 1102562400,
            "name": "\u91cf\u5b50\u4fe1\u606f\u6280\u672f",
            "location": null,
            "teacherName": "\u97e9\u6b63\u752b",
            "periods": 2,
            "additionalInfo": {}
        },
        {
            "py/object": "models.lecture.Lecture",
            "startDate": 1103161500,
            "endDate": 1103167200,
            "name": "\u91cf\u5b50\u4fe1\u606f\u6280\u672f",
            "location": null,
            "teacherName": "\u97e9\u6b63\u752b",
            "periods": 2,
            "additionalInfo": {}
        },
        {
            "py/object": "models.lecture.Lecture",
            "startDate": 1103766300,
            "endDate": 1103772000,
            "name": "\u91cf\u5b50\u4fe1\u606f\u6280\u672f",
            "location": null,
            "teacherName": "\u97e9\u6b63\u752b",
            "periods": 2,
            "additionalInfo": {}
        },
        {
            "py/object": "models.lecture.Lecture",
            "startDate": 1104371100,
            "endDate": 1104376800,
            "name": "\u91cf\u5b50\u4fe1\u606f\u6280\u672f",
            "location": null,
            "teacherName": "\u97e9\u6b63\u752b",
            "periods": 2,
            "additionalInfo": {}
        }
    ],
    "description": "2~18\u5468 null :4(3,4) \u97e9\u6b63\u752b",
    "credit": 3,
    "additionalInfo": {}
}