{
    "py/object": "models.course.Course",
    "id": 92791,
    "name": "\u6982\u7387\u8bba\u4e0e\u6570\u7406\u7edf\u8ba1B",
    "courseCode": "017082",
    "lessonCode": "017082.13",
    "teacherName": "\u80e1\u6cbb\u6c34",
    "lectures": [
        {
            "py/object": "models.lecture.Lecture",
            "startDate": 1351302300,
            "endDate": 1351311000,
            "name": "\u6982\u7387\u8bba\u4e0e\u6570\u7406\u7edf\u8ba1B",
            "location": null,
            "teacherName": "\u80e1\u6cbb\u6c34",
            "periods": 3,
            "additionalInfo": {}
        },
        {
            "py/object": "models.lecture.Lecture",
            "startDate": 1351907100,
            "endDate": 1351915800,
            "name": "\u6982\u7387\u8bba\u4e0e\u6570\u7406\u7edf\u8ba1B",
            "location": null,
            "teacherName": "\u80e1\u6cbb\u6c34",
            "periods": 3,
            "additionalInfo": {}
        },
        {
            "py/object": "models.lecture.Lecture",
            "startDate": 1352511900,
            "endDate": 1352520600,
            "name": "\u6982\u7387\u8bba\u4e0e\u6570\u7406\u7edf\u8ba1B",
            "location": null,
            "teacherName": "\u80e1\u6cbb\u6c34",
            "periods": 3,
            "additionalInfo": {}
        },
        {
            "py/object": "models.lecture.Lecture",
            "startDate": 1353116700,
            "endDate": 1353125400,
            "name": "\u6982\u7387\u8bba\u4e0e\u6570\u7406\u7edf\u8ba1B",
            "location": null,
            "teacherName": "\u80e1\u6cbb\u6c34",
            "periods": 3,
            "additionalInfo": {}
        },
        {
            "py/object": "models.lecture.Lecture",
            "startDate": 1353721500,
            "endDate": 1353730200,
            "name": "\u6982\u7387\u8bba\u4e0e\u6570\u7406\u7edf\u8ba1B",
            "location": null,
            "teacherName": "\u80e1\u6cbb\u6c34",
            "periods": 3,
            "additionalInfo": {}
        },
        {
            "py/object": "models.lecture.Lecture",
            "startDate": 1354326300,
            "endDate": 1354335000,
            "name": "\u6982\u7387\u8bba\u4e0e\u6570\u7406\u7edf\u8ba1B",
            "location": null,
            "teacherName": "\u80e1\u6cbb\u6c34",
            "periods": 3,
            "additionalInfo": {}
        },
        {
            "py/object": "models.lecture.Lecture",
            "startDate": 1354931100,
            "endDate": 1354939800,
            "name": "\u6982\u7387\u8bba\u4e0e\u6570\u7406\u7edf\u8ba1B",
            "location": null,
            "teacherName": "\u80e1\u6cbb\u6c34",
            "periods": 3,
            "additionalInfo": {}
        },
        {
            "py/object": "models.lecture.Lecture",
            "startDate": 1355535900,
            "endDate": 1355544600,
            "name": "\u6982\u7387\u8bba\u4e0e\u6570\u7406\u7edf\u8ba1B",
            "location": null,
            "teacherName": "\u80e1\u6cbb\u6c34",
            "periods": 3,
            "additionalInfo": {}
        },
        {
            "py/object": "models.lecture.Lecture",
            "startDate": 1356140700,
            "endDate": 1356149400,
            "name": "\u6982\u7387\u8bba\u4e0e\u6570\u7406\u7edf\u8ba1B",
            "location": null,
            "teacherName": "\u80e1\u6cbb\u6c34",
            "periods": 3,
            "additionalInfo": {}
        },
        {
            "py/object": "models.lecture.Lecture",
            "startDate": 1356745500,
            "endDate": 1356754200,
            "name": "\u6982\u7387\u8bba\u4e0e\u6570\u7406\u7edf\u8ba1B",
            "location": null,
            "teacherName": "\u80e1\u6cbb\u6c34",
            "periods": 3,
            "additionalInfo": {}
        },
        {
            "py/object": "models.lecture.Lecture",
            "startDate": 1357350300,
            "endDate": 1357359000,
            "name": "\u6982\u7387\u8bba\u4e0e\u6570\u7406\u7edf\u8ba1B",
            "location": null,
            "teacherName": "\u80e1\u6cbb\u6c34",
            "periods": 3,
            "additionalInfo": {}
        },
        {
            "py/object": "models.lecture.Lecture",
            "startDate": 1357955100,
            "endDate": 1357963800,
            "name": "\u6982\u7387\u8bba\u4e0e\u6570\u7406\u7edf\u8ba1B",
            "location": null,
            "teacherName": "\u80e1\u6cbb\u6c34",
            "periods": 3,
            "additionalInfo": {}
        },
        {
            "py/object": "models.lecture.Lecture",
            "startDate": 1358559900,
            "endDate": 1358568600,
            "name": "\u6982\u7387\u8bba\u4e0e\u6570\u7406\u7edf\u8ba1B",
            "location": null,
            "teacherName": "\u80e1\u6cbb\u6c34",
            "periods": 3,
            "additionalInfo": {}
        },
        {
            "py/object": "models.lecture.Lecture",
            "startDate": 1359164700,
            "endDate": 1359173400,
            "name": "\u6982\u7387\u8bba\u4e0e\u6570\u7406\u7edf\u8ba1B",
            "location": null,
            "teacherName": "\u80e1\u6cbb\u6c34",
            "periods": 3,
            "additionalInfo": {}
        },
        {
            "py/object": "models.lecture.Lecture",
            "startDate": 1359769500,
            "endDate": 1359778200,
            "name": "\u6982\u7387\u8bba\u4e0e\u6570\u7406\u7edf\u8ba1B",
            "location": null,
            "teacherName": "\u80e1\u6cbb\u6c34",
            "periods": 3,
            "additionalInfo": {}
        },
        {
            "py/object": "models.lecture.Lecture",
            "startDate": 1360374300,
            "endDate": 1360383000,
            "name": "\u6982\u7387\u8bba\u4e0e\u6570\u7406\u7edf\u8ba1B",
            "location": null,
            "teacherName": "\u80e1\u6cbb\u6c34",
            "periods": 3,
            "additionalInfo": {}
        },
        {
            "py/object": "models.lecture.Lecture",
            "startDate": 1360979100,
            "endDate": 1360987800,
            "name": "\u6982\u7387\u8bba\u4e0e\u6570\u7406\u7edf\u8ba1B",
            "location": null,
            "teacherName": "\u80e1\u6cbb\u6c34",
            "periods": 3,
            "additionalInfo": {}
        },
        {
            "py/object": "models.lecture.Lecture",
            "startDate": 1361583900,
            "endDate": 1361592600,
            "name": "\u6982\u7387\u8bba\u4e0e\u6570\u7406\u7edf\u8ba1B",
            "location": null,
            "teacherName": "\u80e1\u6cbb\u6c34",
            "periods": 3,
            "additionalInfo": {}
        },
        {
            "py/object": "models.lecture.Lecture",
            "startDate": 1362188700,
            "endDate": 1362197400,
            "name": "\u6982\u7387\u8bba\u4e0e\u6570\u7406\u7edf\u8ba1B",
            "location": null,
            "teacherName": "\u80e1\u6cbb\u6c34",
            "periods": 3,
            "additionalInfo": {}
        },
        {
            "py/object": "models.lecture.Lecture",
            "startDate": 1362793500,
            "endDate": 1362802200,
            "name": "\u6982\u7387\u8bba\u4e0e\u6570\u7406\u7edf\u8ba1B",
            "location": null,
            "teacherName": "\u80e1\u6cbb\u6c34",
            "periods": 3,
            "additionalInfo": {}
        }
    ],
    "description": "1~20\u5468 null :6(3,4,5) \u80e1\u6cbb\u6c34",
    "credit": 3,
    "additionalInfo": {}
}