{
    "py/object": "models.course.Course",
    "id": 93243,
    "name": "\u82f1\u8bed\u53e3\u8bed\u5b9e\u8df5",
    "courseCode": "FL1505",
    "lessonCode": "FL1505.09",
    "teacherName": "\u9648\u9759, Billy Elaschuk",
    "lectures": [
        {
            "py/object": "models.lecture.Lecture",
            "startDate": 1505196000,
            "endDate": 1505198700,
            "name": "\u82f1\u8bed\u53e3\u8bed\u5b9e\u8df5",
            "location": "3A104",
            "teacherName": "\u9648\u9759",
            "periods": 1,
            "additionalInfo": {}
        },
        {
            "py/object": "models.lecture.Lecture",
            "startDate": 1505196000,
            "endDate": 1505198700,
            "name": "\u82f1\u8bed\u53e3\u8bed\u5b9e\u8df5",
            "location": "3A104",
            "teacherName": "Billy Elaschuk",
            "periods": 1,
            "additionalInfo": {}
        },
        {
            "py/object": "models.lecture.Lecture",
            "startDate": 1505800800,
            "endDate": 1505803500,
            "name": "\u82f1\u8bed\u53e3\u8bed\u5b9e\u8df5",
            "location": "3A104",
            "teacherName": "\u9648\u9759",
            "periods": 1,
            "additionalInfo": {}
        },
        {
            "py/object": "models.lecture.Lecture",
            "startDate": 1505800800,
            "endDate": 1505803500,
            "name": "\u82f1\u8bed\u53e3\u8bed\u5b9e\u8df5",
            "location": "3A104",
            "teacherName": "Billy Elaschuk",
            "periods": 1,
            "additionalInfo": {}
        },
        {
            "py/object": "models.lecture.Lecture",
            "startDate": 1506405600,
            "endDate": 1506408300,
            "name": "\u82f1\u8bed\u53e3\u8bed\u5b9e\u8df5",
            "location": "3A104",
            "teacherName": "\u9648\u9759",
            "periods": 1,
            "additionalInfo": {}
        },
        {
            "py/object": "models.lecture.Lecture",
            "startDate": 1506405600,
            "endDate": 1506408300,
            "name": "\u82f1\u8bed\u53e3\u8bed\u5b9e\u8df5",
            "location": "3A104",
            "teacherName": "Billy Elaschuk",
            "periods": 1,
            "additionalInfo": {}
        },
        {
            "py/object": "models.lecture.Lecture",
            "startDate": 1507010400,
            "endDate": 1507013100,
            "name": "\u82f1\u8bed\u53e3\u8bed\u5b9e\u8df5",
            "location": "3A104",
            "teacherName": "\u9648\u9759",
            "periods": 1,
            "additionalInfo": {}
        },
        {
            "py/object": "models.lecture.Lecture",
            "startDate": 1507010400,
            "endDate": 1507013100,
            "name": "\u82f1\u8bed\u53e3\u8bed\u5b9e\u8df5",
            "location": "3A104",
            "teacherName": "Billy Elaschuk",
            "periods": 1,
            "additionalInfo": {}
        },
        {
            "py/object": "models.lecture.Lecture",
            "startDate": 1507615200,
            "endDate": 1507617900,
            "name": "\u82f1\u8bed\u53e3\u8bed\u5b9e\u8df5",
            "location": "3A104",
            "teacherName": "\u9648\u9759",
            "periods": 1,
            "additionalInfo": {}
        },
        {
            "py/object": "models.lecture.Lecture",
            "startDate": 1507615200,
            "endDate": 1507617900,
            "name": "\u82f1\u8bed\u53e3\u8bed\u5b9e\u8df5",
            "location": "3A104",
            "teacherName": "Billy Elaschuk",
            "periods": 1,
            "additionalInfo": {}
        },
        {
            "py/object": "models.lecture.Lecture",
            "startDate": 1508220000,
            "endDate": 1508222700,
            "name": "\u82f1\u8bed\u53e3\u8bed\u5b9e\u8df5",
            "location": "3A104",
            "teacherName": "\u9648\u9759",
            "periods": 1,
            "additionalInfo": {}
        },
        {
            "py/object": "models.lecture.Lecture",
            "startDate": 1508220000,
            "endDate": 1508222700,
            "name": "\u82f1\u8bed\u53e3\u8bed\u5b9e\u8df5",
            "location": "3A104",
            "teacherName": "Billy Elaschuk",
            "periods": 1,
            "additionalInfo": {}
        },
        {
            "py/object": "models.lecture.Lecture",
            "startDate": 1508824800,
            "endDate": 1508827500,
            "name": "\u82f1\u8bed\u53e3\u8bed\u5b9e\u8df5",
            "location": "3A104",
            "teacherName": "\u9648\u9759",
            "periods": 1,
            "additionalInfo": {}
        },
        {
            "py/object": "models.lecture.Lecture",
            "startDate": 1508824800,
            "endDate": 1508827500,
            "name": "\u82f1\u8bed\u53e3\u8bed\u5b9e\u8df5",
            "location": "3A104",
            "teacherName": "Billy Elaschuk",
            "periods": 1,
            "additionalInfo": {}
        },
        {
            "py/object": "models.lecture.Lecture",
            "startDate": 1509429600,
            "endDate": 1509432300,
            "name": "\u82f1\u8bed\u53e3\u8bed\u5b9e\u8df5",
            "location": "3A104",
            "teacherName": "\u9648\u9759",
            "periods": 1,
            "additionalInfo": {}
        },
        {
            "py/object": "models.lecture.Lecture",
            "startDate": 1509429600,
            "endDate": 1509432300,
            "name": "\u82f1\u8bed\u53e3\u8bed\u5b9e\u8df5",
            "location": "3A104",
            "teacherName": "Billy Elaschuk",
            "periods": 1,
            "additionalInfo": {}
        },
        {
            "py/object": "models.lecture.Lecture",
            "startDate": 1510034400,
            "endDate": 1510037100,
            "name": "\u82f1\u8bed\u53e3\u8bed\u5b9e\u8df5",
            "location": "3A104",
            "teacherName": "\u9648\u9759",
            "periods": 1,
            "additionalInfo": {}
        },
        {
            "py/object": "models.lecture.Lecture",
            "startDate": 1510034400,
            "endDate": 1510037100,
            "name": "\u82f1\u8bed\u53e3\u8bed\u5b9e\u8df5",
            "location": "3A104",
            "teacherName": "Billy Elaschuk",
            "periods": 1,
            "additionalInfo": {}
        },
        {
            "py/object": "models.lecture.Lecture",
            "startDate": 1510639200,
            "endDate": 1510641900,
            "name": "\u82f1\u8bed\u53e3\u8bed\u5b9e\u8df5",
            "location": "3A104",
            "teacherName": "\u9648\u9759",
            "periods": 1,
            "additionalInfo": {}
        },
        {
            "py/object": "models.lecture.Lecture",
            "startDate": 1510639200,
            "endDate": 1510641900,
            "name": "\u82f1\u8bed\u53e3\u8bed\u5b9e\u8df5",
            "location": "3A104",
            "teacherName": "Billy Elaschuk",
            "periods": 1,
            "additionalInfo": {}
        },
        {
            "py/object": "models.lecture.Lecture",
            "startDate": 1511244000,
            "endDate": 1511246700,
            "name": "\u82f1\u8bed\u53e3\u8bed\u5b9e\u8df5",
            "location": "3A104",
            "teacherName": "\u9648\u9759",
            "periods": 1,
            "additionalInfo": {}
        },
        {
            "py/object": "models.lecture.Lecture",
            "startDate": 1511244000,
            "endDate": 1511246700,
            "name": "\u82f1\u8bed\u53e3\u8bed\u5b9e\u8df5",
            "location": "3A104",
            "teacherName": "Billy Elaschuk",
            "periods": 1,
            "additionalInfo": {}
        },
        {
            "py/object": "models.lecture.Lecture",
            "startDate": 1511848800,
            "endDate": 1511851500,
            "name": "\u82f1\u8bed\u53e3\u8bed\u5b9e\u8df5",
            "location": "3A104",
            "teacherName": "\u9648\u9759",
            "periods": 1,
            "additionalInfo": {}
        },
        {
            "py/object": "models.lecture.Lecture",
            "startDate": 1511848800,
            "endDate": 1511851500,
            "name": "\u82f1\u8bed\u53e3\u8bed\u5b9e\u8df5",
            "location": "3A104",
            "teacherName": "Billy Elaschuk",
            "periods": 1,
            "additionalInfo": {}
        },
        {
            "py/object": "models.lecture.Lecture",
            "startDate": 1512453600,
            "endDate": 1512456300,
            "name": "\u82f1\u8bed\u53e3\u8bed\u5b9e\u8df5",
            "location": "3A104",
            "teacherName": "\u9648\u9759",
            "periods": 1,
            "additionalInfo": {}
        },
        {
            "py/object": "models.lecture.Lecture",
            "startDate": 1512453600,
            "endDate": 1512456300,
            "name": "\u82f1\u8bed\u53e3\u8bed\u5b9e\u8df5",
            "location": "3A104",
            "teacherName": "Billy Elaschuk",
            "periods": 1,
            "additionalInfo": {}
        },
        {
            "py/object": "models.lecture.Lecture",
            "startDate": 1513058400,
            "endDate": 1513061100,
            "name": "\u82f1\u8bed\u53e3\u8bed\u5b9e\u8df5",
            "location": "3A104",
            "teacherName": "\u9648\u9759",
            "periods": 1,
            "additionalInfo": {}
        },
        {
            "py/object": "models.lecture.Lecture",
            "startDate": 1513058400,
            "endDate": 1513061100,
            "name": "\u82f1\u8bed\u53e3\u8bed\u5b9e\u8df5",
            "location": "3A104",
            "teacherName": "Billy Elaschuk",
            "periods": 1,
            "additionalInfo": {}
        },
        {
            "py/object": "models.lecture.Lecture",
            "startDate": 1513663200,
            "endDate": 1513665900,
            "name": "\u82f1\u8bed\u53e3\u8bed\u5b9e\u8df5",
            "location": "3A104",
            "teacherName": "\u9648\u9759",
            "periods": 1,
            "additionalInfo": {}
        },
        {
            "py/object": "models.lecture.Lecture",
            "startDate": 1513663200,
            "endDate": 1513665900,
            "name": "\u82f1\u8bed\u53e3\u8bed\u5b9e\u8df5",
            "location": "3A104",
            "teacherName": "Billy Elaschuk",
            "periods": 1,
            "additionalInfo": {}
        },
        {
            "py/object": "models.lecture.Lecture",
            "startDate": 1514268000,
            "endDate": 1514270700,
            "name": "\u82f1\u8bed\u53e3\u8bed\u5b9e\u8df5",
            "location": "3A104",
            "teacherName": "\u9648\u9759",
            "periods": 1,
            "additionalInfo": {}
        },
        {
            "py/object": "models.lecture.Lecture",
            "startDate": 1514268000,
            "endDate": 1514270700,
            "name": "\u82f1\u8bed\u53e3\u8bed\u5b9e\u8df5",
            "location": "3A104",
            "teacherName": "Billy Elaschuk",
            "periods": 1,
            "additionalInfo": {}
        },
        {
            "py/object": "models.lecture.Lecture",
            "startDate": 1514872800,
            "endDate": 1514875500,
            "name": "\u82f1\u8bed\u53e3\u8bed\u5b9e\u8df5",
            "location": "3A104",
            "teacherName": "\u9648\u9759",
            "periods": 1,
            "additionalInfo": {}
        },
        {
            "py/object": "models.lecture.Lecture",
            "startDate": 1514872800,
            "endDate": 1514875500,
            "name": "\u82f1\u8bed\u53e3\u8bed\u5b9e\u8df5",
            "location": "3A104",
            "teacherName": "Billy Elaschuk",
            "periods": 1,
            "additionalInfo": {}
        }
    ],
    "description": "2~18\u5468 3A104 :2(6,6) \u9648\u9759\n2~18\u5468 3A104 :2(6,6) Billy Elaschuk",
    "credit": 1,
    "additionalInfo": {}
}