{
    "py/object": "models.course.Course",
    "id": 168939,
    "name": "\u9ad8\u7b49\u5de5\u7a0b\u6570\u5b66",
    "courseCode": "INST6101P",
    "lessonCode": "INST6101P.01",
    "teacherName": "\u90d1\u6d25\u6d25",
    "lectures": [
        {
            "py/object": "models.lecture.Lecture",
            "startDate": 1757893800,
            "endDate": 1757899500,
            "name": "\u9ad8\u7b49\u5de5\u7a0b\u6570\u5b66",
            "location": "3B202",
            "teacherName": "\u90d1\u6d25\u6d25",
            "periods": 2,
            "startIndex": 1,
            "endIndex": 2,
            "startHHMM": 750,
            "endHHMM": 925,
            "additionalInfo": {}
        },
        {
            "py/object": "models.lecture.Lecture",
            "startDate": 1758073500,
            "endDate": 1758082200,
            "name": "\u9ad8\u7b49\u5de5\u7a0b\u6570\u5b66",
            "location": "3B202",
            "teacherName": "\u90d1\u6d25\u6d25",
            "periods": 3,
            "startIndex": 3,
            "endIndex": 5,
            "startHHMM": 945,
            "endHHMM": 1210,
            "additionalInfo": {}
        },
        {
            "py/object": "models.lecture.Lecture",
            "startDate": 1758498600,
            "endDate": 1758504300,
            "name": "\u9ad8\u7b49\u5de5\u7a0b\u6570\u5b66",
            "location": "3B202",
            "teacherName": "\u90d1\u6d25\u6d25",
            "periods": 2,
            "startIndex": 1,
            "endIndex": 2,
            "startHHMM": 750,
            "endHHMM": 925,
            "additionalInfo": {}
        },
        {
            "py/object": "models.lecture.Lecture",
            "startDate": 1758678300,
            "endDate": 1758687000,
            "name": "\u9ad8\u7b49\u5de5\u7a0b\u6570\u5b66",
            "location": "3B202",
            "teacherName": "\u90d1\u6d25\u6d25",
            "periods": 3,
            "startIndex": 3,
            "endIndex": 5,
            "startHHMM": 945,
            "endHHMM": 1210,
            "additionalInfo": {}
        },
        {
            "py/object": "models.lecture.Lecture",
            "startDate": 1759103400,
            "endDate": 1759109100,
            "name": "\u9ad8\u7b49\u5de5\u7a0b\u6570\u5b66",
            "location": "3B202",
            "teacherName": "\u90d1\u6d25\u6d25",
            "periods": 2,
            "startIndex": 1,
            "endIndex": 2,
            "startHHMM": 750,
            "endHHMM": 925,
            "additionalInfo": {}
        },
        {
            "py/object": "models.lecture.Lecture",
            "startDate": 1760147100,
            "endDate": 1760155800,
            "name": "\u9ad8\u7b49\u5de5\u7a0b\u6570\u5b66",
            "location": "3B202",
            "teacherName": "\u90d1\u6d25\u6d25",
            "periods": 3,
            "startIndex": 3,
            "endIndex": 5,
            "startHHMM": 945,
            "endHHMM": 1210,
            "additionalInfo": {}
        },
        {
            "py/object": "models.lecture.Lecture",
            "startDate": 1760313000,
            "endDate": 1760318700,
            "name": "\u9ad8\u7b49\u5de5\u7a0b\u6570\u5b66",
            "location": "3B202",
            "teacherName": "\u90d1\u6d25\u6d25",
            "periods": 2,
            "startIndex": 1,
            "endIndex": 2,
            "startHHMM": 750,
            "endHHMM": 925,
            "additionalInfo": {}
        },
        {
            "py/object": "models.lecture.Lecture",
            "startDate": 1760492700,
            "endDate": 1760501400,
            "name": "\u9ad8\u7b49\u5de5\u7a0b\u6570\u5b66",
            "location": "3B202",
            "teacherName": "\u90d1\u6d25\u6d25",
            "periods": 3,
            "startIndex": 3,
            "endIndex": 5,
            "startHHMM": 945,
            "endHHMM": 1210,
            "additionalInfo": {}
        },
        {
            "py/object": "models.lecture.Lecture",
            "startDate": 1760917800,
            "endDate": 1760923500,
            "name": "\u9ad8\u7b49\u5de5\u7a0b\u6570\u5b66",
            "location": "3B202",
            "teacherName": "\u90d1\u6d25\u6d25",
            "periods": 2,
            "startIndex": 1,
            "endIndex": 2,
            "startHHMM": 750,
            "endHHMM": 925,
            "additionalInfo": {}
        },
        {
            "py/object": "models.lecture.Lecture",
            "startDate": 1761097500,
            "endDate": 1761106200,
            "name": "\u9ad8\u7b49\u5de5\u7a0b\u6570\u5b66",
            "location": "3B202",
            "teacherName": "\u90d1\u6d25\u6d25",
            "periods": 3,
            "startIndex": 3,
            "endIndex": 5,
            "startHHMM": 945,
            "endHHMM": 1210,
            "additionalInfo": {}
        },
        {
            "py/object": "models.lecture.Lecture",
            "startDate": 1761522600,
            "endDate": 1761528300,
            "name": "\u9ad8\u7b49\u5de5\u7a0b\u6570\u5b66",
            "location": "3B202",
            "teacherName": "\u90d1\u6d25\u6d25",
            "periods": 2,
            "startIndex": 1,
            "endIndex": 2,
            "startHHMM": 750,
            "endHHMM": 925,
            "additionalInfo": {}
        },
        {
            "py/object": "models.lecture.Lecture",
            "startDate": 1761702300,
            "endDate": 1761711000,
            "name": "\u9ad8\u7b49\u5de5\u7a0b\u6570\u5b66",
            "location": "3B202",
            "teacherName": "\u90d1\u6d25\u6d25",
            "periods": 3,
            "startIndex": 3,
            "endIndex": 5,
            "startHHMM": 945,
            "endHHMM": 1210,
            "additionalInfo": {}
        },
        {
            "py/object": "models.lecture.Lecture",
            "startDate": 1762127400,
            "endDate": 1762133100,
            "name": "\u9ad8\u7b49\u5de5\u7a0b\u6570\u5b66",
            "location": "3B202",
            "teacherName": "\u90d1\u6d25\u6d25",
            "periods": 2,
            "startIndex": 1,
            "endIndex": 2,
            "startHHMM": 750,
            "endHHMM": 925,
            "additionalInfo": {}
        },
        {
            "py/object": "models.lecture.Lecture",
            "startDate": 1762307100,
            "endDate": 1762315800,
            "name": "\u9ad8\u7b49\u5de5\u7a0b\u6570\u5b66",
            "location": "3B202",
            "teacherName": "\u90d1\u6d25\u6d25",
            "periods": 3,
            "startIndex": 3,
            "endIndex": 5,
            "startHHMM": 945,
            "endHHMM": 1210,
            "additionalInfo": {}
        },
        {
            "py/object": "models.lecture.Lecture",
            "startDate": 1762732200,
            "endDate": 1762737900,
            "name": "\u9ad8\u7b49\u5de5\u7a0b\u6570\u5b66",
            "location": "3B202",
            "teacherName": "\u90d1\u6d25\u6d25",
            "periods": 2,
            "startIndex": 1,
            "endIndex": 2,
            "startHHMM": 750,
            "endHHMM": 925,
            "additionalInfo": {}
        },
        {
            "py/object": "models.lecture.Lecture",
            "startDate": 1762911900,
            "endDate": 1762920600,
            "name": "\u9ad8\u7b49\u5de5\u7a0b\u6570\u5b66",
            "location": "3B202",
            "teacherName": "\u90d1\u6d25\u6d25",
            "periods": 3,
            "startIndex": 3,
            "endIndex": 5,
            "startHHMM": 945,
            "endHHMM": 1210,
            "additionalInfo": {}
        },
        {
            "py/object": "models.lecture.Lecture",
            "startDate": 1763337000,
            "endDate": 1763342700,
            "name": "\u9ad8\u7b49\u5de5\u7a0b\u6570\u5b66",
            "location": "3B202",
            "teacherName": "\u90d1\u6d25\u6d25",
            "periods": 2,
            "startIndex": 1,
            "endIndex": 2,
            "startHHMM": 750,
            "endHHMM": 925,
            "additionalInfo": {}
        },
        {
            "py/object": "models.lecture.Lecture",
            "startDate": 1763516700,
            "endDate": 1763525400,
            "name": "\u9ad8\u7b49\u5de5\u7a0b\u6570\u5b66",
            "location": "3B202",
            "teacherName": "\u90d1\u6d25\u6d25",
            "periods": 3,
            "startIndex": 3,
            "endIndex": 5,
            "startHHMM": 945,
            "endHHMM": 1210,
            "additionalInfo": {}
        },
        {
            "py/object": "models.lecture.Lecture",
            "startDate": 1763941800,
            "endDate": 1763947500,
            "name": "\u9ad8\u7b49\u5de5\u7a0b\u6570\u5b66",
            "location": "3B202",
            "teacherName": "\u90d1\u6d25\u6d25",
            "periods": 2,
            "startIndex": 1,
            "endIndex": 2,
            "startHHMM": 750,
            "endHHMM": 925,
            "additionalInfo": {}
        },
        {
            "py/object": "models.lecture.Lecture",
            "startDate": 1764121500,
            "endDate": 1764130200,
            "name": "\u9ad8\u7b49\u5de5\u7a0b\u6570\u5b66",
            "location": "3B202",
            "teacherName": "\u90d1\u6d25\u6d25",
            "periods": 3,
            "startIndex": 3,
            "endIndex": 5,
            "startHHMM": 945,
            "endHHMM": 1210,
            "additionalInfo": {}
        },
        {
            "py/object": "models.lecture.Lecture",
            "startDate": 1764546600,
            "endDate": 1764552300,
            "name": "\u9ad8\u7b49\u5de5\u7a0b\u6570\u5b66",
            "location": "3B202",
            "teacherName": "\u90d1\u6d25\u6d25",
            "periods": 2,
            "startIndex": 1,
            "endIndex": 2,
            "startHHMM": 750,
            "endHHMM": 925,
            "additionalInfo": {}
        },
        {
            "py/object": "models.lecture.Lecture",
            "startDate": 1764726300,
            "endDate": 1764735000,
            "name": "\u9ad8\u7b49\u5de5\u7a0b\u6570\u5b66",
            "location": "3B202",
            "teacherName": "\u90d1\u6d25\u6d25",
            "periods": 3,
            "startIndex": 3,
            "endIndex": 5,
            "startHHMM": 945,
            "endHHMM": 1210,
            "additionalInfo": {}
        },
        {
            "py/object": "models.lecture.Lecture",
            "startDate": 1765151400,
            "endDate": 1765157100,
            "name": "\u9ad8\u7b49\u5de5\u7a0b\u6570\u5b66",
            "location": "3B202",
            "teacherName": "\u90d1\u6d25\u6d25",
            "periods": 2,
            "startIndex": 1,
            "endIndex": 2,
            "startHHMM": 750,
            "endHHMM": 925,
            "additionalInfo": {}
        },
        {
            "py/object": "models.lecture.Lecture",
            "startDate": 1765331100,
            "endDate": 1765339800,
            "name": "\u9ad8\u7b49\u5de5\u7a0b\u6570\u5b66",
            "location": "3B202",
            "teacherName": "\u90d1\u6d25\u6d25",
            "periods": 3,
            "startIndex": 3,
            "endIndex": 5,
            "startHHMM": 945,
            "endHHMM": 1210,
            "additionalInfo": {}
        },
        {
            "py/object": "models.lecture.Lecture",
            "startDate": 1765756200,
            "endDate": 1765761900,
            "name": "\u9ad8\u7b49\u5de5\u7a0b\u6570\u5b66",
            "location": "3B202",
            "teacherName": "\u90d1\u6d25\u6d25",
            "periods": 2,
            "startIndex": 1,
            "endIndex": 2,
            "startHHMM": 750,
            "endHHMM": 925,
            "additionalInfo": {}
        },
        {
            "py/object": "models.lecture.Lecture",
            "startDate": 1765935900,
            "endDate": 1765944600,
            "name": "\u9ad8\u7b49\u5de5\u7a0b\u6570\u5b66",
            "location": "3B202",
            "teacherName": "\u90d1\u6d25\u6d25",
            "periods": 3,
            "startIndex": 3,
            "endIndex": 5,
            "startHHMM": 945,
            "endHHMM": 1210,
            "additionalInfo": {}
        },
        {
            "py/object": "models.lecture.Lecture",
            "startDate": 1766361000,
            "endDate": 1766366700,
            "name": "\u9ad8\u7b49\u5de5\u7a0b\u6570\u5b66",
            "location": "3B202",
            "teacherName": "\u90d1\u6d25\u6d25",
            "periods": 2,
            "startIndex": 1,
            "endIndex": 2,
            "startHHMM": 750,
            "endHHMM": 925,
            "additionalInfo": {}
        },
        {
            "py/object": "models.lecture.Lecture",
            "startDate": 1766540700,
            "endDate": 1766549400,
            "name": "\u9ad8\u7b49\u5de5\u7a0b\u6570\u5b66",
            "location": "3B202",
            "teacherName": "\u90d1\u6d25\u6d25",
            "periods": 3,
            "startIndex": 3,
            "endIndex": 5,
            "startHHMM": 945,
            "endHHMM": 1210,
            "additionalInfo": {}
        },
        {
            "py/object": "models.lecture.Lecture",
            "startDate": 1766965800,
            "endDate": 1766971500,
            "name": "\u9ad8\u7b49\u5de5\u7a0b\u6570\u5b66",
            "location": "3B202",
            "teacherName": "\u90d1\u6d25\u6d25",
            "periods": 2,
            "startIndex": 1,
            "endIndex": 2,
            "startHHMM": 750,
            "endHHMM": 925,
            "additionalInfo": {}
        },
        {
            "py/object": "models.lecture.Lecture",
            "startDate": 1767145500,
            "endDate": 1767154200,
            "name": "\u9ad8\u7b49\u5de5\u7a0b\u6570\u5b66",
            "location": "3B202",
            "teacherName": "\u90d1\u6d25\u6d25",
            "periods": 3,
            "startIndex": 3,
            "endIndex": 5,
            "startHHMM": 945,
            "endHHMM": 1210,
            "additionalInfo": {}
        }
    ],
    "exams": [],
    "dateTimePlacePersonText": "2~4,6~17\u5468 3B202 :1(1,2) \u90d1\u6d25\u6d25\n2~3,6~17\u5468 3B202 :3(3,4,5) \u90d1\u6d25\u6d25\n5\u5468 3B202 :6(3,4,5) \u90d1\u6d25\u6d25",
    "courseType": "\u7406\u8bba\u8bfe",
    "courseGradation": "\u7855\u58eb",
    "courseCategory": "\u7814\u7a76\u751f\u8bfe\u7a0b",
    "educationType": "\u7814\u7a76\u751f",
    "classType": "\u57fa\u7840",
    "openDepartment": "\u7cbe\u5bc6\u673a\u68b0\u4e0e\u7cbe\u5bc6\u4eea\u5668\u7cfb",
    "description": "",
    "credit": 4,
    "additionalInfo": {}
}