{
    "py/object": "models.course.Course",
    "id": 88699,
    "name": "\u6570\u5b57\u903b\u8f91\u7535\u8def\u5b9e\u9a8c",
    "courseCode": "210051",
    "lessonCode": "210051.01",
    "teacherName": "\u675c\u5b8f\u4f1f",
    "lectures": [
        {
            "py/object": "models.lecture.Lecture",
            "startDate": 1272367800,
            "endDate": 1272373500,
            "name": "\u6570\u5b57\u903b\u8f91\u7535\u8def\u5b9e\u9a8c",
            "location": null,
            "teacherName": "\u675c\u5b8f\u4f1f",
            "periods": 2,
            "additionalInfo": {}
        },
        {
            "py/object": "models.lecture.Lecture",
            "startDate": 1272972600,
            "endDate": 1272978300,
            "name": "\u6570\u5b57\u903b\u8f91\u7535\u8def\u5b9e\u9a8c",
            "location": null,
            "teacherName": "\u675c\u5b8f\u4f1f",
            "periods": 2,
            "additionalInfo": {}
        },
        {
            "py/object": "models.lecture.Lecture",
            "startDate": 1273577400,
            "endDate": 1273583100,
            "name": "\u6570\u5b57\u903b\u8f91\u7535\u8def\u5b9e\u9a8c",
            "location": null,
            "teacherName": "\u675c\u5b8f\u4f1f",
            "periods": 2,
            "additionalInfo": {}
        },
        {
            "py/object": "models.lecture.Lecture",
            "startDate": 1274182200,
            "endDate": 1274187900,
            "name": "\u6570\u5b57\u903b\u8f91\u7535\u8def\u5b9e\u9a8c",
            "location": null,
            "teacherName": "\u675c\u5b8f\u4f1f",
            "periods": 2,
            "additionalInfo": {}
        },
        {
            "py/object": "models.lecture.Lecture",
            "startDate": 1274787000,
            "endDate": 1274792700,
            "name": "\u6570\u5b57\u903b\u8f91\u7535\u8def\u5b9e\u9a8c",
            "location": null,
            "teacherName": "\u675c\u5b8f\u4f1f",
            "periods": 2,
            "additionalInfo": {}
        },
        {
            "py/object": "models.lecture.Lecture",
            "startDate": 1275391800,
            "endDate": 1275397500,
            "name": "\u6570\u5b57\u903b\u8f91\u7535\u8def\u5b9e\u9a8c",
            "location": null,
            "teacherName": "\u675c\u5b8f\u4f1f",
            "periods": 2,
            "additionalInfo": {}
        },
        {
            "py/object": "models.lecture.Lecture",
            "startDate": 1275996600,
            "endDate": 1276002300,
            "name": "\u6570\u5b57\u903b\u8f91\u7535\u8def\u5b9e\u9a8c",
            "location": null,
            "teacherName": "\u675c\u5b8f\u4f1f",
            "periods": 2,
            "additionalInfo": {}
        },
        {
            "py/object": "models.lecture.Lecture",
            "startDate": 1276601400,
            "endDate": 1276607100,
            "name": "\u6570\u5b57\u903b\u8f91\u7535\u8def\u5b9e\u9a8c",
            "location": null,
            "teacherName": "\u675c\u5b8f\u4f1f",
            "periods": 2,
            "additionalInfo": {}
        }
    ],
    "description": "9~16\u5468 null :2(11,12) \u675c\u5b8f\u4f1f",
    "credit": 0.5,
    "additionalInfo": {}
}