{
    "py/object": "models.course.Course",
    "id": 100076,
    "name": "\u8fd0\u7b79\u5b66",
    "courseCode": "015122",
    "lessonCode": "015122.01",
    "teacherName": "\u80e1\u8fbe\u6c99",
    "lectures": [
        {
            "py/object": "models.lecture.Lecture",
            "startDate": 1204422300,
            "endDate": 1204428000,
            "name": "\u8fd0\u7b79\u5b66",
            "location": "2504",
            "teacherName": "\u80e1\u8fbe\u6c99",
            "periods": 2,
            "additionalInfo": {}
        },
        {
            "py/object": "models.lecture.Lecture",
            "startDate": 1205027100,
            "endDate": 1205032800,
            "name": "\u8fd0\u7b79\u5b66",
            "location": "2504",
            "teacherName": "\u80e1\u8fbe\u6c99",
            "periods": 2,
            "additionalInfo": {}
        },
        {
            "py/object": "models.lecture.Lecture",
            "startDate": 1205631900,
            "endDate": 1205637600,
            "name": "\u8fd0\u7b79\u5b66",
            "location": "2504",
            "teacherName": "\u80e1\u8fbe\u6c99",
            "periods": 2,
            "additionalInfo": {}
        },
        {
            "py/object": "models.lecture.Lecture",
            "startDate": 1206236700,
            "endDate": 1206242400,
            "name": "\u8fd0\u7b79\u5b66",
            "location": "2504",
            "teacherName": "\u80e1\u8fbe\u6c99",
            "periods": 2,
            "additionalInfo": {}
        },
        {
            "py/object": "models.lecture.Lecture",
            "startDate": 1206841500,
            "endDate": 1206847200,
            "name": "\u8fd0\u7b79\u5b66",
            "location": "2504",
            "teacherName": "\u80e1\u8fbe\u6c99",
            "periods": 2,
            "additionalInfo": {}
        },
        {
            "py/object": "models.lecture.Lecture",
            "startDate": 1207446300,
            "endDate": 1207452000,
            "name": "\u8fd0\u7b79\u5b66",
            "location": "2504",
            "teacherName": "\u80e1\u8fbe\u6c99",
            "periods": 2,
            "additionalInfo": {}
        },
        {
            "py/object": "models.lecture.Lecture",
            "startDate": 1208051100,
            "endDate": 1208056800,
            "name": "\u8fd0\u7b79\u5b66",
            "location": "2504",
            "teacherName": "\u80e1\u8fbe\u6c99",
            "periods": 2,
            "additionalInfo": {}
        },
        {
            "py/object": "models.lecture.Lecture",
            "startDate": 1208655900,
            "endDate": 1208661600,
            "name": "\u8fd0\u7b79\u5b66",
            "location": "2504",
            "teacherName": "\u80e1\u8fbe\u6c99",
            "periods": 2,
            "additionalInfo": {}
        },
        {
            "py/object": "models.lecture.Lecture",
            "startDate": 1209260700,
            "endDate": 1209266400,
            "name": "\u8fd0\u7b79\u5b66",
            "location": "2504",
            "teacherName": "\u80e1\u8fbe\u6c99",
            "periods": 2,
            "additionalInfo": {}
        },
        {
            "py/object": "models.lecture.Lecture",
            "startDate": 1209865500,
            "endDate": 1209871200,
            "name": "\u8fd0\u7b79\u5b66",
            "location": "2504",
            "teacherName": "\u80e1\u8fbe\u6c99",
            "periods": 2,
            "additionalInfo": {}
        },
        {
            "py/object": "models.lecture.Lecture",
            "startDate": 1210470300,
            "endDate": 1210476000,
            "name": "\u8fd0\u7b79\u5b66",
            "location": "2504",
            "teacherName": "\u80e1\u8fbe\u6c99",
            "periods": 2,
            "additionalInfo": {}
        },
        {
            "py/object": "models.lecture.Lecture",
            "startDate": 1211075100,
            "endDate": 1211080800,
            "name": "\u8fd0\u7b79\u5b66",
            "location": "2504",
            "teacherName": "\u80e1\u8fbe\u6c99",
            "periods": 2,
            "additionalInfo": {}
        },
        {
            "py/object": "models.lecture.Lecture",
            "startDate": 1211679900,
            "endDate": 1211685600,
            "name": "\u8fd0\u7b79\u5b66",
            "location": "2504",
            "teacherName": "\u80e1\u8fbe\u6c99",
            "periods": 2,
            "additionalInfo": {}
        },
        {
            "py/object": "models.lecture.Lecture",
            "startDate": 1212284700,
            "endDate": 1212290400,
            "name": "\u8fd0\u7b79\u5b66",
            "location": "2504",
            "teacherName": "\u80e1\u8fbe\u6c99",
            "periods": 2,
            "additionalInfo": {}
        },
        {
            "py/object": "models.lecture.Lecture",
            "startDate": 1212889500,
            "endDate": 1212895200,
            "name": "\u8fd0\u7b79\u5b66",
            "location": "2504",
            "teacherName": "\u80e1\u8fbe\u6c99",
            "periods": 2,
            "additionalInfo": {}
        },
        {
            "py/object": "models.lecture.Lecture",
            "startDate": 1213494300,
            "endDate": 1213500000,
            "name": "\u8fd0\u7b79\u5b66",
            "location": "2504",
            "teacherName": "\u80e1\u8fbe\u6c99",
            "periods": 2,
            "additionalInfo": {}
        },
        {
            "py/object": "models.lecture.Lecture",
            "startDate": 1214099100,
            "endDate": 1214104800,
            "name": "\u8fd0\u7b79\u5b66",
            "location": "2504",
            "teacherName": "\u80e1\u8fbe\u6c99",
            "periods": 2,
            "additionalInfo": {}
        },
        {
            "py/object": "models.lecture.Lecture",
            "startDate": 1214703900,
            "endDate": 1214709600,
            "name": "\u8fd0\u7b79\u5b66",
            "location": "2504",
            "teacherName": "\u80e1\u8fbe\u6c99",
            "periods": 2,
            "additionalInfo": {}
        }
    ],
    "description": "2~19\u5468 2504 :7(3,4) \u80e1\u8fbe\u6c99",
    "credit": 3,
    "additionalInfo": {}
}