{
    "py/object": "models.course.Course",
    "id": 120801,
    "name": "\u6982\u7387\u8bba\u4e0e\u6570\u7406\u7edf\u8ba1B",
    "courseCode": "017082",
    "lessonCode": "017082.03",
    "teacherName": "\u738b\u5360\u950b, \u5434\u8000\u534e",
    "lectures": [
        {
            "py/object": "models.lecture.Lecture",
            "startDate": 1567647900,
            "endDate": 1567656600,
            "name": "\u6982\u7387\u8bba\u4e0e\u6570\u7406\u7edf\u8ba1B",
            "location": "5202",
            "teacherName": "\u5434\u8000\u534e",
            "periods": 3,
            "additionalInfo": {}
        },
        {
            "py/object": "models.lecture.Lecture",
            "startDate": 1567647900,
            "endDate": 1567656600,
            "name": "\u6982\u7387\u8bba\u4e0e\u6570\u7406\u7edf\u8ba1B",
            "location": "5202",
            "teacherName": "\u738b\u5360\u950b",
            "periods": 3,
            "additionalInfo": {}
        },
        {
            "py/object": "models.lecture.Lecture",
            "startDate": 1568252700,
            "endDate": 1568261400,
            "name": "\u6982\u7387\u8bba\u4e0e\u6570\u7406\u7edf\u8ba1B",
            "location": "5202",
            "teacherName": "\u5434\u8000\u534e",
            "periods": 3,
            "additionalInfo": {}
        },
        {
            "py/object": "models.lecture.Lecture",
            "startDate": 1568252700,
            "endDate": 1568261400,
            "name": "\u6982\u7387\u8bba\u4e0e\u6570\u7406\u7edf\u8ba1B",
            "location": "5202",
            "teacherName": "\u738b\u5360\u950b",
            "periods": 3,
            "additionalInfo": {}
        },
        {
            "py/object": "models.lecture.Lecture",
            "startDate": 1568857500,
            "endDate": 1568866200,
            "name": "\u6982\u7387\u8bba\u4e0e\u6570\u7406\u7edf\u8ba1B",
            "location": "5202",
            "teacherName": "\u5434\u8000\u534e",
            "periods": 3,
            "additionalInfo": {}
        },
        {
            "py/object": "models.lecture.Lecture",
            "startDate": 1568857500,
            "endDate": 1568866200,
            "name": "\u6982\u7387\u8bba\u4e0e\u6570\u7406\u7edf\u8ba1B",
            "location": "5202",
            "teacherName": "\u738b\u5360\u950b",
            "periods": 3,
            "additionalInfo": {}
        },
        {
            "py/object": "models.lecture.Lecture",
            "startDate": 1569462300,
            "endDate": 1569471000,
            "name": "\u6982\u7387\u8bba\u4e0e\u6570\u7406\u7edf\u8ba1B",
            "location": "5202",
            "teacherName": "\u5434\u8000\u534e",
            "periods": 3,
            "additionalInfo": {}
        },
        {
            "py/object": "models.lecture.Lecture",
            "startDate": 1569462300,
            "endDate": 1569471000,
            "name": "\u6982\u7387\u8bba\u4e0e\u6570\u7406\u7edf\u8ba1B",
            "location": "5202",
            "teacherName": "\u738b\u5360\u950b",
            "periods": 3,
            "additionalInfo": {}
        },
        {
            "py/object": "models.lecture.Lecture",
            "startDate": 1570067100,
            "endDate": 1570075800,
            "name": "\u6982\u7387\u8bba\u4e0e\u6570\u7406\u7edf\u8ba1B",
            "location": "5202",
            "teacherName": "\u5434\u8000\u534e",
            "periods": 3,
            "additionalInfo": {}
        },
        {
            "py/object": "models.lecture.Lecture",
            "startDate": 1570067100,
            "endDate": 1570075800,
            "name": "\u6982\u7387\u8bba\u4e0e\u6570\u7406\u7edf\u8ba1B",
            "location": "5202",
            "teacherName": "\u738b\u5360\u950b",
            "periods": 3,
            "additionalInfo": {}
        },
        {
            "py/object": "models.lecture.Lecture",
            "startDate": 1570671900,
            "endDate": 1570680600,
            "name": "\u6982\u7387\u8bba\u4e0e\u6570\u7406\u7edf\u8ba1B",
            "location": "5202",
            "teacherName": "\u5434\u8000\u534e",
            "periods": 3,
            "additionalInfo": {}
        },
        {
            "py/object": "models.lecture.Lecture",
            "startDate": 1570671900,
            "endDate": 1570680600,
            "name": "\u6982\u7387\u8bba\u4e0e\u6570\u7406\u7edf\u8ba1B",
            "location": "5202",
            "teacherName": "\u738b\u5360\u950b",
            "periods": 3,
            "additionalInfo": {}
        },
        {
            "py/object": "models.lecture.Lecture",
            "startDate": 1571276700,
            "endDate": 1571285400,
            "name": "\u6982\u7387\u8bba\u4e0e\u6570\u7406\u7edf\u8ba1B",
            "location": "5202",
            "teacherName": "\u5434\u8000\u534e",
            "periods": 3,
            "additionalInfo": {}
        },
        {
            "py/object": "models.lecture.Lecture",
            "startDate": 1571276700,
            "endDate": 1571285400,
            "name": "\u6982\u7387\u8bba\u4e0e\u6570\u7406\u7edf\u8ba1B",
            "location": "5202",
            "teacherName": "\u738b\u5360\u950b",
            "periods": 3,
            "additionalInfo": {}
        },
        {
            "py/object": "models.lecture.Lecture",
            "startDate": 1571881500,
            "endDate": 1571890200,
            "name": "\u6982\u7387\u8bba\u4e0e\u6570\u7406\u7edf\u8ba1B",
            "location": "5202",
            "teacherName": "\u5434\u8000\u534e",
            "periods": 3,
            "additionalInfo": {}
        },
        {
            "py/object": "models.lecture.Lecture",
            "startDate": 1571881500,
            "endDate": 1571890200,
            "name": "\u6982\u7387\u8bba\u4e0e\u6570\u7406\u7edf\u8ba1B",
            "location": "5202",
            "teacherName": "\u738b\u5360\u950b",
            "periods": 3,
            "additionalInfo": {}
        },
        {
            "py/object": "models.lecture.Lecture",
            "startDate": 1572486300,
            "endDate": 1572495000,
            "name": "\u6982\u7387\u8bba\u4e0e\u6570\u7406\u7edf\u8ba1B",
            "location": "5202",
            "teacherName": "\u5434\u8000\u534e",
            "periods": 3,
            "additionalInfo": {}
        },
        {
            "py/object": "models.lecture.Lecture",
            "startDate": 1572486300,
            "endDate": 1572495000,
            "name": "\u6982\u7387\u8bba\u4e0e\u6570\u7406\u7edf\u8ba1B",
            "location": "5202",
            "teacherName": "\u738b\u5360\u950b",
            "periods": 3,
            "additionalInfo": {}
        },
        {
            "py/object": "models.lecture.Lecture",
            "startDate": 1573091100,
            "endDate": 1573099800,
            "name": "\u6982\u7387\u8bba\u4e0e\u6570\u7406\u7edf\u8ba1B",
            "location": "5202",
            "teacherName": "\u5434\u8000\u534e",
            "periods": 3,
            "additionalInfo": {}
        },
        {
            "py/object": "models.lecture.Lecture",
            "startDate": 1573091100,
            "endDate": 1573099800,
            "name": "\u6982\u7387\u8bba\u4e0e\u6570\u7406\u7edf\u8ba1B",
            "location": "5202",
            "teacherName": "\u738b\u5360\u950b",
            "periods": 3,
            "additionalInfo": {}
        },
        {
            "py/object": "models.lecture.Lecture",
            "startDate": 1573695900,
            "endDate": 1573704600,
            "name": "\u6982\u7387\u8bba\u4e0e\u6570\u7406\u7edf\u8ba1B",
            "location": "5202",
            "teacherName": "\u5434\u8000\u534e",
            "periods": 3,
            "additionalInfo": {}
        },
        {
            "py/object": "models.lecture.Lecture",
            "startDate": 1573695900,
            "endDate": 1573704600,
            "name": "\u6982\u7387\u8bba\u4e0e\u6570\u7406\u7edf\u8ba1B",
            "location": "5202",
            "teacherName": "\u738b\u5360\u950b",
            "periods": 3,
            "additionalInfo": {}
        },
        {
            "py/object": "models.lecture.Lecture",
            "startDate": 1574300700,
            "endDate": 1574309400,
            "name": "\u6982\u7387\u8bba\u4e0e\u6570\u7406\u7edf\u8ba1B",
            "location": "5202",
            "teacherName": "\u5434\u8000\u534e",
            "periods": 3,
            "additionalInfo": {}
        },
        {
            "py/object": "models.lecture.Lecture",
            "startDate": 1574300700,
            "endDate": 1574309400,
            "name": "\u6982\u7387\u8bba\u4e0e\u6570\u7406\u7edf\u8ba1B",
            "location": "5202",
            "teacherName": "\u738b\u5360\u950b",
            "periods": 3,
            "additionalInfo": {}
        },
        {
            "py/object": "models.lecture.Lecture",
            "startDate": 1574905500,
            "endDate": 1574914200,
            "name": "\u6982\u7387\u8bba\u4e0e\u6570\u7406\u7edf\u8ba1B",
            "location": "5202",
            "teacherName": "\u5434\u8000\u534e",
            "periods": 3,
            "additionalInfo": {}
        },
        {
            "py/object": "models.lecture.Lecture",
            "startDate": 1574905500,
            "endDate": 1574914200,
            "name": "\u6982\u7387\u8bba\u4e0e\u6570\u7406\u7edf\u8ba1B",
            "location": "5202",
            "teacherName": "\u738b\u5360\u950b",
            "periods": 3,
            "additionalInfo": {}
        },
        {
            "py/object": "models.lecture.Lecture",
            "startDate": 1575510300,
            "endDate": 1575519000,
            "name": "\u6982\u7387\u8bba\u4e0e\u6570\u7406\u7edf\u8ba1B",
            "location": "5202",
            "teacherName": "\u5434\u8000\u534e",
            "periods": 3,
            "additionalInfo": {}
        },
        {
            "py/object": "models.lecture.Lecture",
            "startDate": 1575510300,
            "endDate": 1575519000,
            "name": "\u6982\u7387\u8bba\u4e0e\u6570\u7406\u7edf\u8ba1B",
            "location": "5202",
            "teacherName": "\u738b\u5360\u950b",
            "periods": 3,
            "additionalInfo": {}
        },
        {
            "py/object": "models.lecture.Lecture",
            "startDate": 1576115100,
            "endDate": 1576123800,
            "name": "\u6982\u7387\u8bba\u4e0e\u6570\u7406\u7edf\u8ba1B",
            "location": "5202",
            "teacherName": "\u5434\u8000\u534e",
            "periods": 3,
            "additionalInfo": {}
        },
        {
            "py/object": "models.lecture.Lecture",
            "startDate": 1576115100,
            "endDate": 1576123800,
            "name": "\u6982\u7387\u8bba\u4e0e\u6570\u7406\u7edf\u8ba1B",
            "location": "5202",
            "teacherName": "\u738b\u5360\u950b",
            "periods": 3,
            "additionalInfo": {}
        },
        {
            "py/object": "models.lecture.Lecture",
            "startDate": 1576719900,
            "endDate": 1576728600,
            "name": "\u6982\u7387\u8bba\u4e0e\u6570\u7406\u7edf\u8ba1B",
            "location": "5202",
            "teacherName": "\u5434\u8000\u534e",
            "periods": 3,
            "additionalInfo": {}
        },
        {
            "py/object": "models.lecture.Lecture",
            "startDate": 1576719900,
            "endDate": 1576728600,
            "name": "\u6982\u7387\u8bba\u4e0e\u6570\u7406\u7edf\u8ba1B",
            "location": "5202",
            "teacherName": "\u738b\u5360\u950b",
            "periods": 3,
            "additionalInfo": {}
        },
        {
            "py/object": "models.lecture.Lecture",
            "startDate": 1577324700,
            "endDate": 1577333400,
            "name": "\u6982\u7387\u8bba\u4e0e\u6570\u7406\u7edf\u8ba1B",
            "location": "5202",
            "teacherName": "\u5434\u8000\u534e",
            "periods": 3,
            "additionalInfo": {}
        },
        {
            "py/object": "models.lecture.Lecture",
            "startDate": 1577324700,
            "endDate": 1577333400,
            "name": "\u6982\u7387\u8bba\u4e0e\u6570\u7406\u7edf\u8ba1B",
            "location": "5202",
            "teacherName": "\u738b\u5360\u950b",
            "periods": 3,
            "additionalInfo": {}
        },
        {
            "py/object": "models.lecture.Lecture",
            "startDate": 1577929500,
            "endDate": 1577938200,
            "name": "\u6982\u7387\u8bba\u4e0e\u6570\u7406\u7edf\u8ba1B",
            "location": "5202",
            "teacherName": "\u5434\u8000\u534e",
            "periods": 3,
            "additionalInfo": {}
        },
        {
            "py/object": "models.lecture.Lecture",
            "startDate": 1577929500,
            "endDate": 1577938200,
            "name": "\u6982\u7387\u8bba\u4e0e\u6570\u7406\u7edf\u8ba1B",
            "location": "5202",
            "teacherName": "\u738b\u5360\u950b",
            "periods": 3,
            "additionalInfo": {}
        }
    ],
    "description": "1~18\u5468 5202 :4(3,4,5) \u5434\u8000\u534e\n1~18\u5468 5202 :4(3,4,5) \u738b\u5360\u950b",
    "credit": 3,
    "additionalInfo": {}
}