{
    "py/object": "models.course.Course",
    "id": 116604,
    "name": "\u7a7a\u95f4\u63a2\u6d4b\u4eea\u5668\u539f\u7406\u4e0e\u65b9\u6cd5",
    "courseCode": "007282",
    "lessonCode": "007282.01",
    "teacherName": "\u859b\u5411\u8f89",
    "lectures": [
        {
            "py/object": "models.lecture.Lecture",
            "startDate": 1551686100,
            "endDate": 1551694800,
            "name": "\u7a7a\u95f4\u63a2\u6d4b\u4eea\u5668\u539f\u7406\u4e0e\u65b9\u6cd5",
            "location": "5505",
            "teacherName": "\u859b\u5411\u8f89",
            "periods": 3,
            "additionalInfo": {}
        },
        {
            "py/object": "models.lecture.Lecture",
            "startDate": 1551852000,
            "endDate": 1551857700,
            "name": "\u7a7a\u95f4\u63a2\u6d4b\u4eea\u5668\u539f\u7406\u4e0e\u65b9\u6cd5",
            "location": "5505",
            "teacherName": "\u859b\u5411\u8f89",
            "periods": 2,
            "additionalInfo": {}
        },
        {
            "py/object": "models.lecture.Lecture",
            "startDate": 1552290900,
            "endDate": 1552299600,
            "name": "\u7a7a\u95f4\u63a2\u6d4b\u4eea\u5668\u539f\u7406\u4e0e\u65b9\u6cd5",
            "location": "5505",
            "teacherName": "\u859b\u5411\u8f89",
            "periods": 3,
            "additionalInfo": {}
        },
        {
            "py/object": "models.lecture.Lecture",
            "startDate": 1552456800,
            "endDate": 1552462500,
            "name": "\u7a7a\u95f4\u63a2\u6d4b\u4eea\u5668\u539f\u7406\u4e0e\u65b9\u6cd5",
            "location": "5505",
            "teacherName": "\u859b\u5411\u8f89",
            "periods": 2,
            "additionalInfo": {}
        },
        {
            "py/object": "models.lecture.Lecture",
            "startDate": 1552895700,
            "endDate": 1552904400,
            "name": "\u7a7a\u95f4\u63a2\u6d4b\u4eea\u5668\u539f\u7406\u4e0e\u65b9\u6cd5",
            "location": "5505",
            "teacherName": "\u859b\u5411\u8f89",
            "periods": 3,
            "additionalInfo": {}
        },
        {
            "py/object": "models.lecture.Lecture",
            "startDate": 1553061600,
            "endDate": 1553067300,
            "name": "\u7a7a\u95f4\u63a2\u6d4b\u4eea\u5668\u539f\u7406\u4e0e\u65b9\u6cd5",
            "location": "5505",
            "teacherName": "\u859b\u5411\u8f89",
            "periods": 2,
            "additionalInfo": {}
        },
        {
            "py/object": "models.lecture.Lecture",
            "startDate": 1553666400,
            "endDate": 1553672100,
            "name": "\u7a7a\u95f4\u63a2\u6d4b\u4eea\u5668\u539f\u7406\u4e0e\u65b9\u6cd5",
            "location": "5505",
            "teacherName": "\u859b\u5411\u8f89",
            "periods": 2,
            "additionalInfo": {}
        },
        {
            "py/object": "models.lecture.Lecture",
            "startDate": 1554105300,
            "endDate": 1554114000,
            "name": "\u7a7a\u95f4\u63a2\u6d4b\u4eea\u5668\u539f\u7406\u4e0e\u65b9\u6cd5",
            "location": "5505",
            "teacherName": "\u859b\u5411\u8f89",
            "periods": 3,
            "additionalInfo": {}
        },
        {
            "py/object": "models.lecture.Lecture",
            "startDate": 1554271200,
            "endDate": 1554276900,
            "name": "\u7a7a\u95f4\u63a2\u6d4b\u4eea\u5668\u539f\u7406\u4e0e\u65b9\u6cd5",
            "location": "5505",
            "teacherName": "\u859b\u5411\u8f89",
            "periods": 2,
            "additionalInfo": {}
        },
        {
            "py/object": "models.lecture.Lecture",
            "startDate": 1554710100,
            "endDate": 1554718800,
            "name": "\u7a7a\u95f4\u63a2\u6d4b\u4eea\u5668\u539f\u7406\u4e0e\u65b9\u6cd5",
            "location": "5505",
            "teacherName": "\u859b\u5411\u8f89",
            "periods": 3,
            "additionalInfo": {}
        },
        {
            "py/object": "models.lecture.Lecture",
            "startDate": 1554876000,
            "endDate": 1554881700,
            "name": "\u7a7a\u95f4\u63a2\u6d4b\u4eea\u5668\u539f\u7406\u4e0e\u65b9\u6cd5",
            "location": "5505",
            "teacherName": "\u859b\u5411\u8f89",
            "periods": 2,
            "additionalInfo": {}
        },
        {
            "py/object": "models.lecture.Lecture",
            "startDate": 1555314900,
            "endDate": 1555323600,
            "name": "\u7a7a\u95f4\u63a2\u6d4b\u4eea\u5668\u539f\u7406\u4e0e\u65b9\u6cd5",
            "location": "5505",
            "teacherName": "\u859b\u5411\u8f89",
            "periods": 3,
            "additionalInfo": {}
        },
        {
            "py/object": "models.lecture.Lecture",
            "startDate": 1555480800,
            "endDate": 1555486500,
            "name": "\u7a7a\u95f4\u63a2\u6d4b\u4eea\u5668\u539f\u7406\u4e0e\u65b9\u6cd5",
            "location": "5505",
            "teacherName": "\u859b\u5411\u8f89",
            "periods": 2,
            "additionalInfo": {}
        },
        {
            "py/object": "models.lecture.Lecture",
            "startDate": 1555919700,
            "endDate": 1555928400,
            "name": "\u7a7a\u95f4\u63a2\u6d4b\u4eea\u5668\u539f\u7406\u4e0e\u65b9\u6cd5",
            "location": "5505",
            "teacherName": "\u859b\u5411\u8f89",
            "periods": 3,
            "additionalInfo": {}
        },
        {
            "py/object": "models.lecture.Lecture",
            "startDate": 1556085600,
            "endDate": 1556091300,
            "name": "\u7a7a\u95f4\u63a2\u6d4b\u4eea\u5668\u539f\u7406\u4e0e\u65b9\u6cd5",
            "location": "5505",
            "teacherName": "\u859b\u5411\u8f89",
            "periods": 2,
            "additionalInfo": {}
        },
        {
            "py/object": "models.lecture.Lecture",
            "startDate": 1556524500,
            "endDate": 1556533200,
            "name": "\u7a7a\u95f4\u63a2\u6d4b\u4eea\u5668\u539f\u7406\u4e0e\u65b9\u6cd5",
            "location": "5505",
            "teacherName": "\u859b\u5411\u8f89",
            "periods": 3,
            "additionalInfo": {}
        },
        {
            "py/object": "models.lecture.Lecture",
            "startDate": 1556690400,
            "endDate": 1556696100,
            "name": "\u7a7a\u95f4\u63a2\u6d4b\u4eea\u5668\u539f\u7406\u4e0e\u65b9\u6cd5",
            "location": "5505",
            "teacherName": "\u859b\u5411\u8f89",
            "periods": 2,
            "additionalInfo": {}
        },
        {
            "py/object": "models.lecture.Lecture",
            "startDate": 1557129300,
            "endDate": 1557138000,
            "name": "\u7a7a\u95f4\u63a2\u6d4b\u4eea\u5668\u539f\u7406\u4e0e\u65b9\u6cd5",
            "location": "5505",
            "teacherName": "\u859b\u5411\u8f89",
            "periods": 3,
            "additionalInfo": {}
        },
        {
            "py/object": "models.lecture.Lecture",
            "startDate": 1557295200,
            "endDate": 1557300900,
            "name": "\u7a7a\u95f4\u63a2\u6d4b\u4eea\u5668\u539f\u7406\u4e0e\u65b9\u6cd5",
            "location": "5505",
            "teacherName": "\u859b\u5411\u8f89",
            "periods": 2,
            "additionalInfo": {}
        },
        {
            "py/object": "models.lecture.Lecture",
            "startDate": 1557734100,
            "endDate": 1557742800,
            "name": "\u7a7a\u95f4\u63a2\u6d4b\u4eea\u5668\u539f\u7406\u4e0e\u65b9\u6cd5",
            "location": "5505",
            "teacherName": "\u859b\u5411\u8f89",
            "periods": 3,
            "additionalInfo": {}
        },
        {
            "py/object": "models.lecture.Lecture",
            "startDate": 1557900000,
            "endDate": 1557905700,
            "name": "\u7a7a\u95f4\u63a2\u6d4b\u4eea\u5668\u539f\u7406\u4e0e\u65b9\u6cd5",
            "location": "5505",
            "teacherName": "\u859b\u5411\u8f89",
            "periods": 2,
            "additionalInfo": {}
        },
        {
            "py/object": "models.lecture.Lecture",
            "startDate": 1558338900,
            "endDate": 1558347600,
            "name": "\u7a7a\u95f4\u63a2\u6d4b\u4eea\u5668\u539f\u7406\u4e0e\u65b9\u6cd5",
            "location": "5505",
            "teacherName": "\u859b\u5411\u8f89",
            "periods": 3,
            "additionalInfo": {}
        },
        {
            "py/object": "models.lecture.Lecture",
            "startDate": 1558504800,
            "endDate": 1558510500,
            "name": "\u7a7a\u95f4\u63a2\u6d4b\u4eea\u5668\u539f\u7406\u4e0e\u65b9\u6cd5",
            "location": "5505",
            "teacherName": "\u859b\u5411\u8f89",
            "periods": 2,
            "additionalInfo": {}
        }
    ],
    "description": "2~4,6~13\u5468 5505 :1(8,9,10) \u859b\u5411\u8f89\n2~13\u5468 5505 :3(6,7) \u859b\u5411\u8f89",
    "credit": 3,
    "additionalInfo": {}
}